demucs3/__init__.py
demucs3/__main__.py
demucs3/apply.py
demucs3/audio.py
demucs3/augment.py
demucs3/demucs.py
demucs3/distrib.py
demucs3/ema.py
demucs3/evaluate.py
demucs3/hdemucs.py
demucs3/pretrained.py
demucs3/repitch.py
demucs3/repo.py
demucs3/separate.py
demucs3/solver.py
demucs3/spec.py
demucs3/states.py
demucs3/svd.py
demucs3/train.py
demucs3/utils.py
demucs3/wav.py
demucs3/wdemucs.py
demucs3/grids/__init__.py
demucs3/grids/_explorers.py
demucs3/grids/mdx.py
demucs3/grids/mdx_extra.py
demucs3/grids/mdx_refine.py
demucs3/remote/files.txt
demucs3/remote/mdx.yaml
demucs3/remote/mdx_extra.yaml
demucs3/remote/mdx_extra_q.yaml
demucs3/remote/mdx_q.yaml
demucs3-3.0.1a0.dist-info/LICENSE
demucs3-3.0.1a0.dist-info/METADATA
demucs3-3.0.1a0.dist-info/WHEEL
demucs3-3.0.1a0.dist-info/entry_points.txt
demucs3-3.0.1a0.dist-info/top_level.txt
demucs3-3.0.1a0.dist-info/RECORD
