Metadata-Version: 2.1
Name: demucs3
Version: 3.0.1a0
Summary: Music source separation in the waveform domain.
Home-page: https://github.com/facebookresearch/demucs
Author: Alexandre Défossez
Author-email: defossez@fb.com
License: MIT License
Platform: UNKNOWN
Classifier: License :: OSI Approved :: MIT License
Classifier: Topic :: Multimedia :: Sound/Audio
Classifier: Topic :: Scientific/Engineering :: Artificial Intelligence
Requires-Python: >=3.7.0
Requires-Dist: dora-search
Requires-Dist: diffq (>=0.2.1)
Requires-Dist: julius (>=0.2.3)
Requires-Dist: lameenc (>=1.2)
Requires-Dist: openunmix
Requires-Dist: pyyaml
Requires-Dist: torch (>=1.8.1)
Requires-Dist: torchaudio (>=0.8)
Requires-Dist: tqdm
Provides-Extra: dev
Requires-Dist: dora-search ; extra == 'dev'
Requires-Dist: diffq (>=0.2.1) ; extra == 'dev'
Requires-Dist: flake8 ; extra == 'dev'
Requires-Dist: hydra-colorlog (>=1.1) ; extra == 'dev'
Requires-Dist: hydra-core (>=1.1) ; extra == 'dev'
Requires-Dist: julius (>=0.2.3) ; extra == 'dev'
Requires-Dist: lameenc (>=1.2) ; extra == 'dev'
Requires-Dist: museval ; extra == 'dev'
Requires-Dist: mypy ; extra == 'dev'
Requires-Dist: openunmix ; extra == 'dev'
Requires-Dist: pyyaml ; extra == 'dev'
Requires-Dist: submitit ; extra == 'dev'
Requires-Dist: torch (>=1.8.1) ; extra == 'dev'
Requires-Dist: torchaudio (>=0.8) ; extra == 'dev'
Requires-Dist: tqdm ; extra == 'dev'
Requires-Dist: treetable ; extra == 'dev'
